{"source/main.ptx": ["exsol-2454"], "source/meta_frontmatter.ptx": ["meta_frontmatter", "meta_frontmatter-preface"], "source/ch_exsel.ptx": ["ch_listas"], "source/sec_ex_taylor.ptx": ["sec_taylor"], "source/sec_ex_curvas.ptx": ["sec_curvas"], "source/sec_ex_func.ptx": ["sec_func"], "source/sec_ex_limcont.ptx": ["sec_limcont"], "source/sec_ex_derdifpt.ptx": ["sec_derdifpt"], "source/sec_ex_cadeia.ptx": ["sec_cadeia"], "source/sec_ex_grad-dir.ptx": ["sec_grad-dir"], "source/sec_ex_curvasR3.ptx": ["sec_curvasR3"], "source/sec_ex_supptddir.ptx": ["sec_supptddir"], "source/sec_ex_maxminloc.ptx": ["sec_maxminloc"], "source/sec_ex_maxmincpt.ptx": ["sec_maxmincpt"], "source/sec_ex_maxminarb.ptx": ["sec_maxminarb"], "source/ch_2023.ptx": ["ch_2023"], "source/sec_2023-p1.ptx": ["sec_2023-p1"], "source/ch_2022.ptx": ["ch_2022"], "source/sec_2022-p1.ptx": ["sec_2022-p1"], "source/sec_2022-p2.ptx": ["sec_2022-p2"], "source/sec_2022-psub.ptx": ["sec_2022-psub"], "source/sec_2022-prec.ptx": ["sec_2022-prec"], "source/ch_2021.ptx": ["ch_2021"], "source/sec_2021-p1.ptx": ["sec_2021-p1"], "source/ch_2020.ptx": ["ch_2020"], "source/sec_2020-p1.ptx": ["sec_2020-p1"], "source/ch_antigas.ptx": ["ch_antigas"], "source/meta_backmatter.ptx": ["meta_backmatter", "apendice"], "source/ap_calc1.ptx": ["ap_calc1"], "source/ap_func.ptx": ["ap_func"], "source/ap_limcont.ptx": ["ap_limcont"], "source/ap_diff.ptx": ["ap_diff"], "source/ap_derivseg.ptx": ["ap_derivseg"], "source/ap_cadeiadir.ptx": ["ap_cadeiadir"], "source/ap_supnivel.ptx": ["ap_supnivel"], "source/ap_maxminloc.ptx": ["ap_maxminloc"], "source/ap_maxmincond.ptx": ["ap_maxmincond"]}